microframe/__init__.py
microframe/core/__init__.py
microframe/core/indexers.py
microframe/core/manipulators.py
microframe/core/microframe.py
microframe/core/printers.py
microframe/readers/__init__.py
microframe/readers/readers.py
microframe/readers/utils/__init__.py
microframe/readers/utils/csv_utils.py
microframe-0.1.0.dist-info/METADATA
microframe-0.1.0.dist-info/WHEEL
microframe-0.1.0.dist-info/licenses/LICENSE.txt
microframe-0.1.0.dist-info/RECORD
