Metadata-Version: 2.1
Name: microframe
Version: 0.1.0
Summary: Lightweight data structure for data handling and analysis in Python
Project-URL: Homepage, https://github.com/cmsolson75/MicroFrame
Project-URL: Bug Tracker, https://github.com/cmsolson75/MicroFrame/issues
Project-URL: Documentation, https://cmsolson75.github.io/MicroFrame/
Author-email: Cameron Olson <cmsolson75@gmail.com>
License-File: LICENSE.txt
Classifier: License :: OSI Approved :: MIT License
Classifier: Operating System :: OS Independent
Classifier: Programming Language :: Python :: 3
Requires-Python: >=3.8
Requires-Dist: numpy>=1.26.0
Provides-Extra: dev
Requires-Dist: black>=23.10.1; extra == 'dev'
Requires-Dist: furo>=2023.9.10; extra == 'dev'
Requires-Dist: hatch>=1.7.0; extra == 'dev'
Requires-Dist: hypothesis>=6.88.3; extra == 'dev'
Requires-Dist: m2r2>=0.3.3.post2; extra == 'dev'
Requires-Dist: pytest-cov>=4.1.0; extra == 'dev'
Requires-Dist: pytest-lazy-fixture>=0.6.3; extra == 'dev'
Requires-Dist: pytest>=7.4.2; extra == 'dev'
Requires-Dist: sphinx>=7.2.6; extra == 'dev'
